CHANGES.txt
MANIFEST.in
NOTICE.txt
README
README.md
setup.py
examples/client.cfg.template
examples/simple.cfg.template
stillson/__init__.py
stillson/stillson.py
stillson.egg-info/PKG-INFO
stillson.egg-info/SOURCES.txt
stillson.egg-info/dependency_links.txt
stillson.egg-info/entry_points.txt
stillson.egg-info/requires.txt
stillson.egg-info/top_level.txt
test/test_stillson.py