Metadata-Version: 1.0
Name: stillson
Version: 0.1.1
Summary: Tool for generating config files using a template and environment variables.
Home-page: https://github.com/mortardata/stillson/
Author: Mortar Data
Author-email: info@mortardata.com
License: LICENSE
Platform: UNKNOWN
